uw_libraries/VERSION
uw_libraries/__init__.py
uw_libraries/dao.py
uw_libraries/models.py
uw_libraries/mylib.py
uw_libraries/subject_guides.py
uw_libraries/test.py
uw_libraries/util.py
uw_libraries/resources/libcurrics/file/currics_db/api/v1/data/course/2015/AUT/MATH/309/A
uw_libraries/resources/libcurrics/file/currics_db/api/v1/data/defaultGuide/tacoma
uw_libraries/resources/libraries/file/mylibinfo/v1/_id_badjsonuser
uw_libraries/resources/libraries/file/mylibinfo/v1/_id_invalidnetid
uw_libraries/resources/libraries/file/mylibinfo/v1/_id_javerage
uw_libraries/resources/libraries/file/mylibinfo/v1/_id_javerage_style_html
uw_libraries/resources/libraries/file/mylibinfo/v1/_id_javerage_style_json
uw_libraries/resources/libraries/file/mylibinfo/v1/_id_javerage_timestamp_1391122522900_style_html
uw_libraries/resources/libraries/file/mylibinfo/v1/_id_jbothell
uw_libraries/resources/libraries/file/mylibinfo/v1/_id_jbothell_style_json
uw_libraries/resources/libraries/file/mylibinfo/v1/_id_jinternational
uw_libraries/resources/libraries/file/mylibinfo/v1/_id_jinternational_style_json
uw_libraries/resources/libraries/file/mylibinfo/v1/_id_jnewstudent
uw_libraries/resources/libraries/file/mylibinfo/v1/_id_jnewstudent_style_json
uw_libraries/resources/libraries/file/mylibinfo/v1/_id_none
uw_libraries/resources/libraries/file/mylibinfo/v1/_id_none_style_json
uw_libraries/tests/__init__.py
uw_libraries/tests/test_daos.py
uw_libraries/tests/test_mylib.py
uw_libraries/tests/test_subject_guides.py
uw_restclients_libraries-1.3.3.dist-info/licenses/LICENSE
uw_restclients_libraries-1.3.3.dist-info/METADATA
uw_restclients_libraries-1.3.3.dist-info/WHEEL
uw_restclients_libraries-1.3.3.dist-info/top_level.txt
uw_restclients_libraries-1.3.3.dist-info/RECORD
